{
    "fields": [
        {
            "metadata": {},
            "name": "clientPerformance",
            "nullable": true,
            "type": {
                "containsNull": true,
                "elementType": {
                    "fields": [
                        {
                            "metadata": {},
                            "name": "clientProcess",
                            "nullable": true,
                            "type": {
                                "fields": [
                                    {
                                        "metadata": {},
                                        "name": "count",
                                        "nullable": true,
                                        "type": "double"
                                    },
                                    {
                                        "metadata": {},
                                        "name": "max",
                                        "nullable": true,
                                        "type": "double"
                                    },
                                    {
                                        "metadata": {},
                                        "name": "min",
                                        "nullable": true,
                                        "type": "double"
                                    },
                                    {
                                        "metadata": {},
                                        "name": "sampledValue",
                                        "nullable": true,
                                        "type": "double"
                                    },
                                    {
                                        "metadata": {},
                                        "name": "stdDev",
                                        "nullable": true,
                                        "type": "double"
                                    },
                                    {
                                        "metadata": {},
                                        "name": "value",
                                        "nullable": true,
                                        "type": "double"
                                    }
                                ],
                                "type": "struct"
                            }
                        },
                        {
                            "metadata": {},
                            "name": "name",
                            "nullable": true,
                            "type": "string"
                        },
                        {
                            "metadata": {},
                            "name": "networkConnection",
                            "nullable": true,
                            "type": {
                                "fields": [
                                    {
                                        "metadata": {},
                                        "name": "count",
                                        "nullable": true,
                                        "type": "double"
                                    },
                                    {
                                        "metadata": {},
                                        "name": "max",
                                        "nullable": true,
                                        "type": "double"
                                    },
                                    {
                                        "metadata": {},
                                        "name": "min",
                                        "nullable": true,
                                        "type": "double"
                                    },
                                    {
                                        "metadata": {},
                                        "name": "sampledValue",
                                        "nullable": true,
                                        "type": "double"
                                    },
                                    {
                                        "metadata": {},
                                        "name": "stdDev",
                                        "nullable": true,
                                        "type": "double"
                                    },
                                    {
                                        "metadata": {},
                                        "name": "value",
                                        "nullable": true,
                                        "type": "double"
                                    }
                                ],
                                "type": "struct"
                            }
                        },
                        {
                            "metadata": {},
                            "name": "receiveRequest",
                            "nullable": true,
                            "type": {
                                "fields": [
                                    {
                                        "metadata": {},
                                        "name": "count",
                                        "nullable": true,
                                        "type": "double"
                                    },
                                    {
                                        "metadata": {},
                                        "name": "max",
                                        "nullable": true,
                                        "type": "double"
                                    },
                                    {
                                        "metadata": {},
                                        "name": "min",
                                        "nullable": true,
                                        "type": "double"
                                    },
                                    {
                                        "metadata": {},
                                        "name": "sampledValue",
                                        "nullable": true,
                                        "type": "double"
                                    },
                                    {
                                        "metadata": {},
                                        "name": "stdDev",
                                        "nullable": true,
                                        "type": "double"
                                    },
                                    {
                                        "metadata": {},
                                        "name": "value",
                                        "nullable": true,
                                        "type": "double"
                                    }
                                ],
                                "type": "struct"
                            }
                        },
                        {
                            "metadata": {},
                            "name": "sendRequest",
                            "nullable": true,
                            "type": {
                                "fields": [
                                    {
                                        "metadata": {},
                                        "name": "count",
                                        "nullable": true,
                                        "type": "double"
                                    },
                                    {
                                        "metadata": {},
                                        "name": "max",
                                        "nullable": true,
                                        "type": "double"
                                    },
                                    {
                                        "metadata": {},
                                        "name": "min",
                                        "nullable": true,
                                        "type": "double"
                                    },
                                    {
                                        "metadata": {},
                                        "name": "sampledValue",
                                        "nullable": true,
                                        "type": "double"
                                    },
                                    {
                                        "metadata": {},
                                        "name": "stdDev",
                                        "nullable": true,
                                        "type": "double"
                                    },
                                    {
                                        "metadata": {},
                                        "name": "value",
                                        "nullable": true,
                                        "type": "double"
                                    }
                                ],
                                "type": "struct"
                            }
                        },
                        {
                            "metadata": {},
                            "name": "total",
                            "nullable": true,
                            "type": {
                                "fields": [
                                    {
                                        "metadata": {},
                                        "name": "count",
                                        "nullable": true,
                                        "type": "double"
                                    },
                                    {
                                        "metadata": {},
                                        "name": "max",
                                        "nullable": true,
                                        "type": "double"
                                    },
                                    {
                                        "metadata": {},
                                        "name": "min",
                                        "nullable": true,
                                        "type": "double"
                                    },
                                    {
                                        "metadata": {},
                                        "name": "sampledValue",
                                        "nullable": true,
                                        "type": "double"
                                    },
                                    {
                                        "metadata": {},
                                        "name": "stdDev",
                                        "nullable": true,
                                        "type": "double"
                                    },
                                    {
                                        "metadata": {},
                                        "name": "value",
                                        "nullable": true,
                                        "type": "double"
                                    }
                                ],
                                "type": "struct"
                            }
                        },
                        {
                            "metadata": {},
                            "name": "url",
                            "nullable": true,
                            "type": "string"
                        },
                        {
                            "metadata": {},
                            "name": "urlData",
                            "nullable": true,
                            "type": {
                                "fields": [
                                    {
                                        "metadata": {},
                                        "name": "base",
                                        "nullable": true,
                                        "type": "string"
                                    },
                                    {
                                        "metadata": {},
                                        "name": "hashTag",
                                        "nullable": true,
                                        "type": "string"
                                    },
                                    {
                                        "metadata": {},
                                        "name": "host",
                                        "nullable": true,
                                        "type": "string"
                                    },
                                    {
                                        "metadata": {},
                                        "name": "protocol",
                                        "nullable": true,
                                        "type": "string"
                                    }
                                ],
                                "type": "struct"
                            }
                        }
                    ],
                    "type": "struct"
                },
                "type": "array"
            }
        },
        {
            "metadata": {},
            "name": "context",
            "nullable": true,
            "type": {
                "fields": [
                    {
                        "metadata": {},
                        "name": "data",
                        "nullable": true,
                        "type": {
                            "fields": [
                                {
                                    "metadata": {},
                                    "name": "eventTime",
                                    "nullable": true,
                                    "type": "string"
                                },
                                {
                                    "metadata": {},
                                    "name": "isSynthetic",
                                    "nullable": true,
                                    "type": "boolean"
                                },
                                {
                                    "metadata": {},
                                    "name": "samplingRate",
                                    "nullable": true,
                                    "type": "double"
                                }
                            ],
                            "type": "struct"
                        }
                    },
                    {
                        "metadata": {},
                        "name": "device",
                        "nullable": true,
                        "type": {
                            "fields": [
                                {
                                    "metadata": {},
                                    "name": "browser",
                                    "nullable": true,
                                    "type": "string"
                                },
                                {
                                    "metadata": {},
                                    "name": "browserVersion",
                                    "nullable": true,
                                    "type": "string"
                                },
                                {
                                    "metadata": {},
                                    "name": "deviceModel",
                                    "nullable": true,
                                    "type": "string"
                                },
                                {
                                    "metadata": {},
                                    "name": "deviceName",
                                    "nullable": true,
                                    "type": "string"
                                },
                                {
                                    "metadata": {},
                                    "name": "id",
                                    "nullable": true,
                                    "type": "string"
                                },
                                {
                                    "metadata": {},
                                    "name": "osVersion",
                                    "nullable": true,
                                    "type": "string"
                                },
                                {
                                    "metadata": {},
                                    "name": "type",
                                    "nullable": true,
                                    "type": "string"
                                }
                            ],
                            "type": "struct"
                        }
                    },
                    {
                        "metadata": {},
                        "name": "location",
                        "nullable": true,
                        "type": {
                            "fields": [
                                {
                                    "metadata": {},
                                    "name": "city",
                                    "nullable": true,
                                    "type": "string"
                                },
                                {
                                    "metadata": {},
                                    "name": "clientip",
                                    "nullable": true,
                                    "type": "string"
                                },
                                {
                                    "metadata": {},
                                    "name": "continent",
                                    "nullable": true,
                                    "type": "string"
                                },
                                {
                                    "metadata": {},
                                    "name": "country",
                                    "nullable": true,
                                    "type": "string"
                                },
                                {
                                    "metadata": {},
                                    "name": "province",
                                    "nullable": true,
                                    "type": "string"
                                }
                            ],
                            "type": "struct"
                        }
                    },
                    {
                        "metadata": {},
                        "name": "operation",
                        "nullable": true,
                        "type": {
                            "fields": [
                                {
                                    "metadata": {},
                                    "name": "id",
                                    "nullable": true,
                                    "type": "string"
                                },
                                {
                                    "metadata": {},
                                    "name": "name",
                                    "nullable": true,
                                    "type": "string"
                                },
                                {
                                    "metadata": {},
                                    "name": "parentId",
                                    "nullable": true,
                                    "type": "string"
                                }
                            ],
                            "type": "struct"
                        }
                    },
                    {
                        "metadata": {},
                        "name": "session",
                        "nullable": true,
                        "type": {
                            "fields": [
                                {
                                    "metadata": {},
                                    "name": "id",
                                    "nullable": true,
                                    "type": "string"
                                },
                                {
                                    "metadata": {},
                                    "name": "isFirst",
                                    "nullable": true,
                                    "type": "boolean"
                                }
                            ],
                            "type": "struct"
                        }
                    },
                    {
                        "metadata": {},
                        "name": "user",
                        "nullable": true,
                        "type": {
                            "fields": [
                                {
                                    "metadata": {},
                                    "name": "anonId",
                                    "nullable": true,
                                    "type": "string"
                                },
                                {
                                    "metadata": {},
                                    "name": "isAuthenticated",
                                    "nullable": true,
                                    "type": "boolean"
                                }
                            ],
                            "type": "struct"
                        }
                    }
                ],
                "type": "struct"
            }
        },
        {
            "metadata": {},
            "name": "internal",
            "nullable": true,
            "type": {
                "fields": [
                    {
                        "metadata": {},
                        "name": "data",
                        "nullable": true,
                        "type": {
                            "fields": [
                                {
                                    "metadata": {},
                                    "name": "documentVersion",
                                    "nullable": true,
                                    "type": "string"
                                },
                                {
                                    "metadata": {},
                                    "name": "id",
                                    "nullable": true,
                                    "type": "string"
                                }
                            ],
                            "type": "struct"
                        }
                    }
                ],
                "type": "struct"
            }
        }
    ],
    "type": "struct"
}